pycashflow/__init__.py
pycashflow-0.0.0.post1.dist-info/METADATA
pycashflow-0.0.0.post1.dist-info/WHEEL
pycashflow-0.0.0.post1.dist-info/top_level.txt
pycashflow-0.0.0.post1.dist-info/RECORD
