Metadata-Version: 2.1
Name: pycashflow
Version: 0.0.0.post1
Summary: Easy manipulation of financial models.
